reprexlite/__init__.py
reprexlite/__main__.py
reprexlite/cli.py
reprexlite/code.py
reprexlite/formatting.py
reprexlite/ipython.py
reprexlite/reprex.py
reprexlite/session_info.py
reprexlite/version.py
reprexlite-0.5.0.dist-info/LICENSE
reprexlite-0.5.0.dist-info/METADATA
reprexlite-0.5.0.dist-info/WHEEL
reprexlite-0.5.0.dist-info/entry_points.txt
reprexlite-0.5.0.dist-info/top_level.txt
reprexlite-0.5.0.dist-info/RECORD
