Metadata-Version: 2.1
Name: reprexlite
Version: 0.5.0
Summary: Render reproducible examples of Python code for sharing.
Home-page: https://github.com/jayqi/reprexlite
Author: Jay Qi
Author-email: jayqi.opensource@gmail.com
License: MIT
Project-URL: Bug Tracker, https://github.com/jayqi/reprexlite/issues
Project-URL: Documentation, https://jayqi.github.io/reprexlite/
Project-URL: Source Code, https://github.com/jayqi/reprexlite
Platform: UNKNOWN
Classifier: Intended Audience :: Developers
Classifier: License :: OSI Approved :: MIT License
Classifier: Operating System :: OS Independent
Classifier: Programming Language :: Python :: 3
Classifier: Programming Language :: Python :: 3.6
Classifier: Programming Language :: Python :: 3.7
Classifier: Programming Language :: Python :: 3.8
Classifier: Programming Language :: Python :: 3.9
Requires-Python: >=3.6
Requires-Dist: libcst
Requires-Dist: typer
Requires-Dist: importlib-metadata ; python_version < "3.8"
Provides-Extra: black
Requires-Dist: black ; extra == 'black'
Provides-Extra: ipython
Requires-Dist: ipython ; extra == 'ipython'
Provides-Extra: pygments
Requires-Dist: Pygments ; extra == 'pygments'
